celescope/__init__.py
celescope/celescope.py
celescope/chemistry_dict.py
celescope/data/__init__.py
celescope/data/Clindex/tag_barcode.fasta
celescope/data/Clindex/tag_linker.fasta
celescope/data/HLA/hla_reference_rna.fasta
celescope/data/chemistry/__init__.py
celescope/data/chemistry/5p3p-1/bc1.txt
celescope/data/chemistry/5p3p-1/bc2.txt
celescope/data/chemistry/5p3p-1/bc3.txt
celescope/data/chemistry/5p3p-2/bc1.txt
celescope/data/chemistry/5p3p-2/bc2.txt
celescope/data/chemistry/5p3p-2/bc3.txt
celescope/data/chemistry/5p3p-3/bc1.txt
celescope/data/chemistry/5p3p-3/bc2.txt
celescope/data/chemistry/5p3p-3/bc3.txt
celescope/data/chemistry/GEXSCOPE-V1/bc.txt
celescope/data/chemistry/GEXSCOPE-V1/linker1.txt
celescope/data/chemistry/GEXSCOPE-V1/linker2.txt
celescope/data/chemistry/GEXSCOPE-V2/bc1.txt
celescope/data/chemistry/GEXSCOPE-V2/bc2.txt
celescope/data/chemistry/GEXSCOPE-V2/bc3.txt
celescope/data/chemistry/GEXSCOPE-V2/linker1.txt
celescope/data/chemistry/GEXSCOPE-V2/linker2.txt
celescope/data/chemistry/GEXSCOPE-V3/bc1.txt
celescope/data/chemistry/GEXSCOPE-V3/bc2.txt
celescope/data/chemistry/GEXSCOPE-V3/bc3.txt
celescope/data/chemistry/GEXSCOPE-V3/linker1.txt
celescope/data/chemistry/GEXSCOPE-V3/linker2.txt
celescope/data/chemistry/bulk_rna-V1/bc.txt
celescope/data/chemistry/bulk_rna-V2/bc.txt
celescope/data/chemistry/bulk_rna-bulk_vdj_match/bc.txt
celescope/data/chemistry/bulk_vdj/bc.txt
celescope/data/chemistry/bulk_vdj/linker.txt
celescope/data/chemistry/flv/bc.txt
celescope/data/chemistry/flv/linker
celescope/data/chemistry/flv_rna/bc.txt
celescope/data/chemistry/flv_rna/linker_4types
celescope/data/chemistry/flv_rna-V2/bc1.txt
celescope/data/chemistry/flv_rna-V2/bc2.txt
celescope/data/chemistry/flv_rna-V2/bc3.txt
celescope/data/chemistry/flv_rna-V2/linker1.txt
celescope/data/chemistry/flv_rna-V2/linker2.txt
celescope/data/chemistry/flv_rna-V2/linker3.txt
celescope/data/fusion/blood_1/BCR_ABL1_PML_RARA_all.fasta
celescope_rnavirus-1.0.1.dist-info/licenses/LICENSE
celescope_rnavirus-1.0.1.dist-info/METADATA
celescope_rnavirus-1.0.1.dist-info/WHEEL
celescope_rnavirus-1.0.1.dist-info/entry_points.txt
celescope_rnavirus-1.0.1.dist-info/top_level.txt
celescope_rnavirus-1.0.1.dist-info/RECORD
